setup.py
compiledtrees/__init__.py
compiledtrees/code_gen.py
compiledtrees/compiled.py
compiledtrees/setup.py
sklearn_compiledtrees.egg-info/PKG-INFO
sklearn_compiledtrees.egg-info/SOURCES.txt
sklearn_compiledtrees.egg-info/dependency_links.txt
sklearn_compiledtrees.egg-info/not-zip-safe
sklearn_compiledtrees.egg-info/top_level.txt