Metadata-Version: 1.1
Name: sklearn-compiledtrees
Version: 1.0.3
Summary: Compiled scikit-learn decision trees for faster evaluation
Home-page: https://github.com/ajtulloch/sklearn-compiledtrees
Author: Andrew Tulloch
Author-email: andrew@tullo.ch
License: BSD License
Platform: Any
Classifier: Intended Audience :: Science/Research
Classifier: Intended Audience :: Developers
Classifier: License :: OSI Approved
Classifier: Programming Language :: C
Classifier: Programming Language :: Python
Classifier: Topic :: Software Development
Classifier: Topic :: Scientific/Engineering
Classifier: Operating System :: Microsoft :: Windows
Classifier: Operating System :: POSIX
Classifier: Operating System :: Unix
Classifier: Operating System :: MacOS
Classifier: Programming Language :: Python :: 2
Classifier: Programming Language :: Python :: 2.7
